seaturtle_flowchart/__init__.py
seaturtle_flowchart/__version__.py
seaturtle_flowchart-0.0.1.dist-info/LICENSE
seaturtle_flowchart-0.0.1.dist-info/METADATA
seaturtle_flowchart-0.0.1.dist-info/WHEEL
seaturtle_flowchart-0.0.1.dist-info/top_level.txt
seaturtle_flowchart-0.0.1.dist-info/RECORD
