Metadata-Version: 2.1
Name: seaturtle_flowchart
Version: 0.0.1
Summary: Python files used as databases.
Author: Tathya Garg
Author-email: Tathya Garg <coding.tathya@gmail.com>
License: MIT License
Keywords: database
Classifier: Development Status :: 3 - Alpha
Classifier: Intended Audience :: Developers
Classifier: License :: OSI Approved :: MIT License
Classifier: Programming Language :: Python
Classifier: Programming Language :: Python :: 3.12
Requires-Python: >=3.12
License-File: LICENSE
